cloudx_iaas_api/__init__.py
cloudx_iaas_api/cluster_management.py
cloudx_iaas_api-1.2.13.data/scripts/cloudx
cloudx_paas_api/__init__.py
cloudx_paas_api/monitoring_management.py
cloudx_paas_api/smart_dns_management.py
cloudx_iaas_api-1.2.13.dist-info/LICENSE
cloudx_iaas_api-1.2.13.dist-info/METADATA
cloudx_iaas_api-1.2.13.dist-info/WHEEL
cloudx_iaas_api-1.2.13.dist-info/top_level.txt
cloudx_iaas_api-1.2.13.dist-info/RECORD
